lumivox/__init__.py
lumivox/core.py
lumivox/utils.py
lumivox/__pycache__/__init__.cpython-39.pyc
lumivox/__pycache__/core.cpython-39.pyc
lumivox/__pycache__/utils.cpython-39.pyc
lumivox-0.15.0.dist-info/METADATA
lumivox-0.15.0.dist-info/WHEEL
lumivox-0.15.0.dist-info/top_level.txt
lumivox-0.15.0.dist-info/RECORD
